{
  "packageDirectories": [
    {
      "path": "./test-data/"
    },
    {
      "path": "./code-analyzer",
      "default": true,
      "package": "CopadoSFDXAnalyzer",
      "versionName": "ver 2.0",
      "versionNumber": "2.0.2.NEXT",
      "dependencies": [
        {
          "package": "copadoDeployer@25.0"
        },
        {
          "package": "copadoQIF@4.0"
        }
      ]
    }
  ],
  "name": "CopadoSFDXAnalyzer",
  "namespace": "",
  "sfdcLoginUrl": "https://login.salesforce.com",
  "sourceApiVersion": "64.0",
  "packageAliases": {
    "CopadoSFDXAnalyzer": "0Ho8Z0000004CEDSA2",
    "copadoDeployer@25.0": "04tKA000000cBc4",
    "copadoQIF@4.0": "04tP7000001gwztIAA",
    "CopadoSFDXAnalyzer@0.1.0-1": "04t8Z000000UeXNQA0",
    "CopadoSFDXAnalyzer@2.0.2-1": "04t8Z000000BooeQAC"
  }
}
