{
  "packageDirectories": [
    {
      "path": "./code-analyzer",
      "default": true,
      "package": "CopadoSFDXAnalyzer",
      "versionName": "ver 2.0",
      "versionNumber": "2.0.0.NEXT",
      "dependencies": [
        {
          "package": "copadoDeployer@21.4"
        },
        {
          "package": "copadoDX@4.19"
        },
        {
          "package": "copadoQIF@1.42"
        }
      ]
    }
  ],
  "name": "CopadoSFDXAnalyzer",
  "namespace": "",
  "sfdcLoginUrl": "https://login.salesforce.com",
  "sourceApiVersion": "55.0",
  "packageAliases": {
    "CopadoSFDXAnalyzer": "0Ho8Z0000004CEDSA2",
    "copadoDeployer@21.4": "04t5p000001E97y",
    "copadoDX@4.19": "04tP7000000057lIAA",
    "copadoQIF@1.42": "04tP700000002EjIAI",
    "CopadoSFDXAnalyzer@0.1.0-1": "04t8Z000000UeXNQA0",
    "CopadoSFDXAnalyzer@0.1.0-3": "04t8Z000000BooFQAS"
  }
}
